easydl/__init__.py
easydl/proto/__init__.py
easydl/proto/easydl_pb2.py
easydl/proto/easydl_pb2_grpc.py
easydl/python/__init__.py
easydl/python/common/__init__.py
easydl/python/common/constants.py
easydl/python/common/log_utils.py
easydl/python/runtime/__init__.py
easydl/python/runtime/easydl_client.py
easydl/python/runtime/metric_collector.py
easydl/python/runtime/resource_optimizer.py
easydl_sdk-0.0.1rc0.dist-info/LICENSE
easydl_sdk-0.0.1rc0.dist-info/METADATA
easydl_sdk-0.0.1rc0.dist-info/WHEEL
easydl_sdk-0.0.1rc0.dist-info/top_level.txt
easydl_sdk-0.0.1rc0.dist-info/RECORD
