Metadata-Version: 2.1
Name: easydl-sdk
Version: 0.0.1rc0
Summary: The EasyDL client to connect the EasyDL server.
Home-page: https://elasticdl.org
Author: Ant Group
License: UNKNOWN
Platform: UNKNOWN
Requires-Python: >=3.5
Requires-Dist: grpcio (==1.34.1)
Requires-Dist: grpcio-tools (==1.34.1)
Requires-Dist: protobuf (>=3.12.0)
Requires-Dist: psutil
